zmazino/__init__.py
zmazino/logger.py
zmazino-0.0.6.dist-info/LICENSE.txt
zmazino-0.0.6.dist-info/METADATA
zmazino-0.0.6.dist-info/WHEEL
zmazino-0.0.6.dist-info/entry_points.txt
zmazino-0.0.6.dist-info/top_level.txt
zmazino-0.0.6.dist-info/RECORD
