Metadata-Version: 2.1
Name: zmazino
Version: 0.0.6
Summary: Modern utils library
Home-page: https://github.com/mazino2d/zmazino
Author: Khoi Dang Do
Author-email: mazino2d@gmail.com
License: MIT
Keywords: utils
Platform: UNKNOWN
Requires-Python: >=3.5, <4
